multicall/__init__.py
multicall/call.py
multicall/constants.py
multicall/exceptions.py
multicall/loggers.py
multicall/multicall.py
multicall/py.typed
multicall/signature.py
multicall/utils.py
multicall-0.15.1.dist-info/METADATA
multicall-0.15.1.dist-info/WHEEL
multicall-0.15.1.dist-info/RECORD
