Metadata-Version: 2.1
Name: multicall
Version: 0.15.1
Summary: aggregate results from multiple ethereum contract calls
Author: banteg
Requires-Python: >=3.10,<4
Classifier: Programming Language :: Python :: 3
Classifier: Programming Language :: Python :: 3.10
Classifier: Programming Language :: Python :: 3.11
Classifier: Programming Language :: Python :: 3.12
Requires-Dist: cchecksum (>=0.0.3,<1)
Requires-Dist: eth_retry (>=0.3.5)
Requires-Dist: faster-eth-abi (>=5.2.1,<6)
Requires-Dist: web3 (>=5.27,!=5.29.*,!=5.30.*,!=5.31.0,!=5.31.1,!=5.31.2)
